{
  "version": "7",
  "dialect": "postgresql",
  "entries": [
    {
      "idx": 0,
      "version": "7",
      "when": 1781350271143,
      "tag": "0000_quick_moon_knight",
      "breakpoints": true
    },
    {
      "idx": 1,
      "version": "7",
      "when": 1781351414171,
      "tag": "0001_cleanup_legacy_indexes",
      "breakpoints": true
    },
    {
      "idx": 2,
      "version": "7",
      "when": 1781351507442,
      "tag": "0002_sync_published_index",
      "breakpoints": true
    },
    {
      "idx": 3,
      "version": "7",
      "when": 1781351920869,
      "tag": "0003_add_rate_limits",
      "breakpoints": true
    },
    {
      "idx": 4,
      "version": "7",
      "when": 1781352298597,
      "tag": "0004_unique_account_hosts",
      "breakpoints": true
    },
    {
      "idx": 5,
      "version": "7",
      "when": 1781357738039,
      "tag": "0005_cute_killmonger",
      "breakpoints": true
    },
    {
      "idx": 6,
      "version": "7",
      "when": 1781358373382,
      "tag": "0006_quick_gambit",
      "breakpoints": true
    },
    {
      "idx": 7,
      "version": "7",
      "when": 1781362901347,
      "tag": "0007_little_drax",
      "breakpoints": true
    },
    {
      "idx": 8,
      "version": "7",
      "when": 1781365161057,
      "tag": "0008_dizzy_gwen_stacy",
      "breakpoints": true
    },
    {
      "idx": 9,
      "version": "7",
      "when": 1781452800000,
      "tag": "0009_unique_attached_host",
      "breakpoints": true
    },
    {
      "idx": 10,
      "version": "7",
      "when": 1781452900000,
      "tag": "0010_thick_human_robot",
      "breakpoints": true
    },
    {
      "idx": 11,
      "version": "7",
      "when": 1781494099114,
      "tag": "0011_spooky_tempest",
      "breakpoints": true
    },
    {
      "idx": 12,
      "version": "7",
      "when": 1781681038977,
      "tag": "0012_public_page_lookup_indexes",
      "breakpoints": true
    },
    {
      "idx": 13,
      "version": "7",
      "when": 1783430400000,
      "tag": "0013_follow_up_sequences",
      "breakpoints": true
    },
    {
      "idx": 14,
      "version": "7",
      "when": 1783468800000,
      "tag": "0014_brand_default_palette",
      "breakpoints": true
    },
    {
      "idx": 15,
      "version": "7",
      "when": 1783472400000,
      "tag": "0015_account_calendar_integration",
      "breakpoints": true
    }
  ]
}
